{
  "description": "A score-scope frost demo that starts from a three-note cluster and renders four staggered frost iterations.",
  "motifs": {
    "low": ["330.00:1.0"],
    "mid": ["440.00:1.0"],
    "high": ["550.00:1.0"]
  },
  "composition": {
    "voices": [
      {
        "phrases": [
          {
            "motifs": ["low"]
          }
        ]
      },
      {
        "phrases": [
          {
            "motifs": ["mid"]
          }
        ]
      },
      {
        "phrases": [
          {
            "motifs": ["high"]
          }
        ]
      }
    ],
    "score_transforms": [
      {
        "name": "frost_effect",
        "params": {
          "iterations": 4
        }
      }
    ]
  }
}
